jsonutils/__init__.py
jsonutils/base.py
jsonutils/cache.py
jsonutils/encoders.py
jsonutils/exceptions.py
jsonutils/query.py
jsonutils/release.py
jsonutils/validation.py
jsonutils/config/__init__.py
jsonutils/config/completion.py
jsonutils/config/locals.py
jsonutils/config/queries.py
jsonutils/functions/__init__.py
jsonutils/functions/actions.py
jsonutils/functions/decorators.py
jsonutils/functions/dummy.py
jsonutils/functions/external.py
jsonutils/functions/parsers.py
jsonutils/functions/reader.py
jsonutils/functions/seekers.py
jsonutils/functions/validator.py
jsonutils/tests/__init__.py
jsonutils/tests/test_atomic_transactions.py
jsonutils/tests/test_config.py
jsonutils/tests/test_copy.py
jsonutils/tests/test_dict.py
jsonutils/tests/test_group_operations.py
jsonutils/tests/test_json.py
jsonutils/tests/test_json_build_from_path.py
jsonutils/tests/test_json_merge.py
jsonutils/tests/test_read_html_tables.py
jsonutils/tests/test_single_queries.py
jsonutils/tests/test_singletons.py
jsonutils/tests/test_url_validator.py
jsonutils/utils/__init__.py
jsonutils/utils/dict.py
jsonutils/utils/retry.py
jsonutils/utils/urls.py
json_queries-0.1.16.dist-info/METADATA
json_queries-0.1.16.dist-info/WHEEL
json_queries-0.1.16.dist-info/top_level.txt
json_queries-0.1.16.dist-info/RECORD
