Metadata-Version: 2.1
Name: json-queries
Version: 0.1.16
Summary: Translates Django ORM query system to json objects
Home-page: https://github.com/donielix/jsonutils
Author: Daniel Diego Horcajuelo
Author-email: dadiego91@gmail.com
Project-URL: Bug Reports, https://github.com/donielix/jsonutils/issues
Project-URL: Source, https://github.com/donielix/jsonutils
Keywords: json,query,django,orm
Classifier: Development Status :: 3 - Alpha
Classifier: Intended Audience :: Developers
Classifier: Topic :: Software Development :: Build Tools
Classifier: License :: OSI Approved :: GNU General Public License v3 (GPLv3)
Classifier: Programming Language :: Python :: 3
Classifier: Programming Language :: Python :: 3.8
Classifier: Programming Language :: Python :: 3.9
Classifier: Programming Language :: Python :: 3 :: Only
Requires-Python: >=3.8, <4
Requires-Dist: requests
Requires-Dist: pytz
Requires-Dist: beautifulsoup4
Requires-Dist: pyperclip
